datatables_mongoengine/__init__.py
datatables_mongoengine/datatables.py
datatables_mongoengine-0.1.7.dist-info/LICENSE.txt
datatables_mongoengine-0.1.7.dist-info/METADATA
datatables_mongoengine-0.1.7.dist-info/WHEEL
datatables_mongoengine-0.1.7.dist-info/top_level.txt
datatables_mongoengine-0.1.7.dist-info/RECORD
