Metadata-Version: 2.1
Name: datatables-mongoengine
Version: 0.1.7
Summary: MongoEngine QuerySet class for populating DataTables from MongoEngine.
Home-page: https://github.com/pauljolsen/datatables-mongoengine
Author: Paul Olsen
Author-email: paul@wholeshoot.com
License: MIT
Keywords: flask django mongoengine mongodb
Platform: UNKNOWN
Classifier: Development Status :: 3 - Alpha
Classifier: License :: OSI Approved :: MIT License
Classifier: Programming Language :: Python :: 3.7
Classifier: Topic :: Database :: Database Engines/Servers
Requires-Dist: mongoengine
